{"days":{"2026-07-03":{"website":{"up":6,"total":6,"msSum":7940},"api":{"up":6,"total":6,"msSum":8531},"database":{"up":6,"total":6,"msSum":8531},"search":{"up":6,"total":6,"msSum":8531},"docs":{"up":6,"total":6,"msSum":15838}},"2026-07-04":{"website":{"up":15,"total":15,"msSum":5642},"api":{"up":15,"total":15,"msSum":7843},"database":{"up":15,"total":15,"msSum":7843},"search":{"up":15,"total":15,"msSum":7843},"docs":{"up":15,"total":15,"msSum":3689}},"2026-07-05":{"website":{"up":15,"total":15,"msSum":6076},"api":{"up":15,"total":15,"msSum":7283},"database":{"up":15,"total":15,"msSum":7283},"search":{"up":15,"total":15,"msSum":7283},"docs":{"up":15,"total":15,"msSum":4081}},"2026-07-06":{"website":{"up":5,"total":5,"msSum":1712},"api":{"up":5,"total":5,"msSum":2484},"database":{"up":5,"total":5,"msSum":2484},"search":{"up":5,"total":5,"msSum":2484},"docs":{"up":5,"total":5,"msSum":1298}}},"current":{"website":{"ok":true,"ms":440},"api":{"ok":true,"ms":452},"database":{"ok":true,"ms":452},"search":{"ok":true,"ms":452},"docs":{"ok":true,"ms":156}},"incidents":[],"lastHour":"2026-07-06T17","updated":"2026-07-06T17:27:26.381Z"}